{"name":"Send a Message","id":"contact-us;send-a-message","testSteps":[{"number":1,"description":"Given Navigate to Page Contact Us","duration":8188,"startTime":"2021-04-10T12:27:40.810-05:00[America/Bogota]","screenshots":[{"screenshot":"ae6b3215096c25b07796e58eea2e9477705b9262a1cb7b57cc293c9419132fa8.png","timeStamp":1618075661336},{"screenshot":"7861ce8fc7bc7169574d16eee10bdf107f52bad2eda721e48eea84c39f42a232.png","timeStamp":1618075668998}],"result":"SUCCESS","precondition":false,"level":0},{"number":2,"description":"When A User enters values to send","duration":944,"startTime":"2021-04-10T12:27:48.998-05:00[America/Bogota]","screenshots":[{"screenshot":"b37d036be57a9874202da6affa2ce6dadfdc6d3bb0b9a51d324978386a996a00.png","timeStamp":1618075669942}],"result":"SUCCESS","precondition":false,"level":0},{"number":3,"description":"And A User clicks on Send button 2","duration":6285,"startTime":"2021-04-10T12:27:49.942-05:00[America/Bogota]","screenshots":[{"screenshot":"e4ca422d6260ee52c9c132cbd8340dee18076f308a1424f24ab036a9f432dab0.png","timeStamp":1618075676227}],"result":"SUCCESS","precondition":false,"level":0},{"number":4,"description":"Then Application shows an success message","duration":448,"startTime":"2021-04-10T12:27:56.227-05:00[America/Bogota]","screenshots":[{"screenshot":"e4ca422d6260ee52c9c132cbd8340dee18076f308a1424f24ab036a9f432dab0.png","timeStamp":1618075676675}],"result":"SUCCESS","precondition":false,"level":0}],"userStory":{"id":"contact-us","storyName":"Contact Us","path":"ContactUs.feature","type":"feature"},"featureTag":{"name":"Contact Us","type":"feature","displayName":"Contact Us"},"title":"Send a Message","description":"","tags":[{"name":"Contact Us","type":"feature","displayName":"Contact Us"},{"name":"contactus","type":"tag","displayName":"contactus"}],"startTime":"2021-04-10T12:27:38.705-05:00[America/Bogota]","duration":18658,"projectKey":"","driver":"chrome","isManualTestingUpToDate":false,"manual":false,"testSource":"Cucumber","actors":[{"name":"actorWeb","can":["browse the web"]}],"result":"SUCCESS"}